apple_mango/mango.py
apple_mango-0.2.dist-info/DESCRIPTION.rst
apple_mango-0.2.dist-info/METADATA
apple_mango-0.2.dist-info/RECORD
apple_mango-0.2.dist-info/WHEEL
apple_mango-0.2.dist-info/metadata.json
apple_mango-0.2.dist-info/top_level.txt
mango/mango.py
