Metadata-Version: 2.0
Name: apple-mango
Version: 0.2
Summary: Light weight BDD Pattern
Home-page: https://github.com/legshort/apple-mango/
Author: Jun Young Lee
Author-email: legshort@gmail.com
License: MIT
Keywords: tdd,bdd,test
Platform: UNKNOWN
Classifier: Programming Language :: Python
Classifier: Programming Language :: Python :: 3
Classifier: License :: OSI Approved :: BSD License
Requires-Dist: wrapt (>=1.10.0)
